pyiron_atomistics/__init__.py
pyiron_atomistics/_tests.py
pyiron_atomistics/_version.py
pyiron_atomistics/project.py
pyiron_atomistics/toolkit.py
pyiron_atomistics/atomistics/__init__.py
pyiron_atomistics/atomistics/generic/__init__.py
pyiron_atomistics/atomistics/generic/object_type.py
pyiron_atomistics/atomistics/job/__init__.py
pyiron_atomistics/atomistics/job/atomistic.py
pyiron_atomistics/atomistics/job/interactive.py
pyiron_atomistics/atomistics/job/interactivewrapper.py
pyiron_atomistics/atomistics/job/potentials.py
pyiron_atomistics/atomistics/job/sqs.py
pyiron_atomistics/atomistics/job/structurecontainer.py
pyiron_atomistics/atomistics/master/__init__.py
pyiron_atomistics/atomistics/master/elasticmatrix.py
pyiron_atomistics/atomistics/master/murnaghan.py
pyiron_atomistics/atomistics/master/parallel.py
pyiron_atomistics/atomistics/master/phonopy.py
pyiron_atomistics/atomistics/master/quasi.py
pyiron_atomistics/atomistics/master/sqsmaster.py
pyiron_atomistics/atomistics/master/structure.py
pyiron_atomistics/atomistics/structure/__init__.py
pyiron_atomistics/atomistics/structure/analyse.py
pyiron_atomistics/atomistics/structure/atom.py
pyiron_atomistics/atomistics/structure/atoms.py
pyiron_atomistics/atomistics/structure/factory.py
pyiron_atomistics/atomistics/structure/has_structure.py
pyiron_atomistics/atomistics/structure/neighbors.py
pyiron_atomistics/atomistics/structure/periodic_table.py
pyiron_atomistics/atomistics/structure/phonopy.py
pyiron_atomistics/atomistics/structure/pyironase.py
pyiron_atomistics/atomistics/structure/pyscal.py
pyiron_atomistics/atomistics/structure/pyxtal.py
pyiron_atomistics/atomistics/structure/structurestorage.py
pyiron_atomistics/atomistics/structure/factories/__init__.py
pyiron_atomistics/atomistics/structure/factories/aimsgb.py
pyiron_atomistics/atomistics/structure/factories/ase.py
pyiron_atomistics/atomistics/structure/factories/atomsk.py
pyiron_atomistics/atomistics/structure/factories/compound.py
pyiron_atomistics-0.8.7.dist-info/METADATA
pyiron_atomistics-0.8.7.dist-info/WHEEL
pyiron_atomistics-0.8.7.dist-info/licenses/LICENSE
pyiron_atomistics-0.8.7.dist-info/RECORD
