Metadata-Version: 2.4
Name: pyiron_atomistics
Version: 0.8.7
Summary: An interface to atomistic simulation codes including but not limited to GPAW, LAMMPS, S/Phi/nX and VASP.
Project-URL: Homepage, https://pyiron.org
Project-URL: Documentation, https://pyiron.readthedocs.io
Project-URL: Repository, https://github.com/pyiron/pyiron_atomistics
Author-email: "Max-Planck-Institut für Eisenforschung GmbH - Computational Materials Design (CM) Department" <pyiron@mpie.de>
License: BSD 3-Clause License
License-File: LICENSE
Keywords: pyiron
Classifier: Development Status :: 5 - Production/Stable
Classifier: Intended Audience :: Science/Research
Classifier: License :: OSI Approved :: BSD License
Classifier: Operating System :: OS Independent
Classifier: Programming Language :: Python :: 3.11
Classifier: Programming Language :: Python :: 3.12
Classifier: Programming Language :: Python :: 3.13
Classifier: Topic :: Scientific/Engineering :: Physics
Requires-Python: <3.14,>=3.11
Requires-Dist: ase<=3.27.0,>=3.23.0
Requires-Dist: assyst<=0.11.0,>=0.9.0
Requires-Dist: atomistics<=0.3.5,>=0.3.0
Requires-Dist: defusedxml<=0.7.1,>=0.7.0
Requires-Dist: h5py<=3.15.1,>=3.12.1
Requires-Dist: matplotlib<=3.10.8,>=3.9.1
Requires-Dist: mendeleev==1.1.0
Requires-Dist: mp-api<=0.45.15,>=0.37.0
Requires-Dist: numpy<=2.3.5,>=2.2.1
Requires-Dist: pandas<=2.3.3,>=2.2.3
Requires-Dist: phonopy<=2.47.1,>=2.26.6
Requires-Dist: pint<=0.25.2,>=0.24.4
Requires-Dist: pyiron-base<=0.15.12,>=0.15.4
Requires-Dist: pyiron-lammps<=0.5.2,>=0.3.2
Requires-Dist: pyiron-snippets<=1.0.2,>=1.0.1
Requires-Dist: pyiron-vasp<=0.2.18,>=0.2.2
Requires-Dist: pylammpsmpi<=0.3.8,>=0.2.36
Requires-Dist: pyscal3<=3.3.0,>=3.2.5
Requires-Dist: scikit-learn<=1.8.0,>=1.4.2
Requires-Dist: scipy<=1.16.3,>=1.15.0
Requires-Dist: seekpath<=2.1.0,>=1.9.5
Requires-Dist: spglib<=2.7.0,>=2.5.0
Requires-Dist: sphinx-parser==0.1.6
Requires-Dist: structuretoolkit<=0.0.39,>=0.0.35
